fastapi_mike-1.0.0.dist-info/licenses/LICENSE
fastmike/__init__.py
fastmike/__main__.py
fastmike/cli.py
fastmike/templates.py
fastmike/utils.py
fastapi_mike-1.0.0.dist-info/METADATA
fastapi_mike-1.0.0.dist-info/WHEEL
fastapi_mike-1.0.0.dist-info/entry_points.txt
fastapi_mike-1.0.0.dist-info/top_level.txt
fastapi_mike-1.0.0.dist-info/RECORD
