Metadata-Version: 2.4
Name: fastapi-mike
Version: 1.0.0
Summary: Enterprise FastAPI Scaffolder with Auth, Admin and Docker
Author-email: Mike Cardona <mikecardona076@gmail.com>
Requires-Python: >=3.8
License-File: LICENSE
Requires-Dist: click>=8.0.0
Requires-Dist: fastapi>=0.100.0
Requires-Dist: uvicorn[standard]>=0.22.0
Requires-Dist: sqlalchemy>=2.0.0
Requires-Dist: alembic>=1.10.0
Requires-Dist: requests>=2.28.0
Requires-Dist: sqladmin>=0.11.0
Requires-Dist: passlib[bcrypt]>=1.7.4
Requires-Dist: python-jose[cryptography]>=3.3.0
Requires-Dist: python-multipart>=0.0.6
Requires-Dist: pydantic-settings>=2.0.0
Dynamic: license-file
